LICENSE.md
MANIFEST.in
README.md
setup.py
sas_frontend/__init__.py
sas_frontend/authorize.html
sas_frontend/index.html
sas_frontend/onboarding.html
sas_frontend/robots.txt
sas_frontend/service_worker.js
sas_frontend.egg-info/PKG-INFO
sas_frontend.egg-info/SOURCES.txt
sas_frontend.egg-info/dependency_links.txt
sas_frontend.egg-info/not-zip-safe
sas_frontend.egg-info/top_level.txt
sas_frontend/frontend_es5/01fec74d.js
sas_frontend/frontend_es5/01fec74d.js.gz
sas_frontend/frontend_es5/02093421.js
sas_frontend/frontend_es5/02093421.js.gz
sas_frontend/frontend_es5/0321e042.js
sas_frontend/frontend_es5/0321e042.js.LICENSE.txt
sas_frontend/frontend_es5/0321e042.js.gz
sas_frontend/frontend_es5/0388d839.js
sas_frontend/frontend_es5/0388d839.js.gz
sas_frontend/frontend_es5/03f28c63.js
sas_frontend/frontend_es5/03f28c63.js.gz
sas_frontend/frontend_es5/0432d19c.js
sas_frontend/frontend_es5/0432d19c.js.LICENSE.txt
sas_frontend/frontend_es5/0432d19c.js.gz
sas_frontend/frontend_es5/052ad1aa.js
sas_frontend/frontend_es5/052ad1aa.js.gz
sas_frontend/frontend_es5/05ba9e3e.js
sas_frontend/frontend_es5/05ba9e3e.js.gz
sas_frontend/frontend_es5/0603a87f.js
sas_frontend/frontend_es5/0603a87f.js.LICENSE.txt
sas_frontend/frontend_es5/0603a87f.js.gz
sas_frontend/frontend_es5/06a9b1b1.js
sas_frontend/frontend_es5/06a9b1b1.js.LICENSE.txt
sas_frontend/frontend_es5/06a9b1b1.js.gz
sas_frontend/frontend_es5/06afa7c3.js
sas_frontend/frontend_es5/06afa7c3.js.gz
sas_frontend/frontend_es5/0746279c.js
sas_frontend/frontend_es5/0746279c.js.gz
sas_frontend/frontend_es5/087c4876.js
sas_frontend/frontend_es5/087c4876.js.gz
sas_frontend/frontend_es5/090484ad.js
sas_frontend/frontend_es5/090484ad.js.gz
sas_frontend/frontend_es5/09864804.js
sas_frontend/frontend_es5/09864804.js.LICENSE.txt
sas_frontend/frontend_es5/09864804.js.gz
sas_frontend/frontend_es5/0a2667d3.js
sas_frontend/frontend_es5/0a2667d3.js.gz
sas_frontend/frontend_es5/0a7e612d.js
sas_frontend/frontend_es5/0a7e612d.js.LICENSE.txt
sas_frontend/frontend_es5/0a7e612d.js.gz
sas_frontend/frontend_es5/0adb4449.js
sas_frontend/frontend_es5/0adb4449.js.gz
sas_frontend/frontend_es5/0b745ff6.js
