Metadata-Version: 1.0
Name: sas-frontend
Version: 20211007.3
Summary: The SmartAutomatic frontend
Home-page: UNKNOWN
Author: UNKNOWN
Author-email: UNKNOWN
License: Apache-2.0
Platform: UNKNOWN
